render9_otp/__init__.py
render9_otp/functions.py
render9_otp-0.2.2.dist-info/METADATA
render9_otp-0.2.2.dist-info/WHEEL
render9_otp-0.2.2.dist-info/top_level.txt
render9_otp-0.2.2.dist-info/RECORD
