Metadata-Version: 2.1
Name: render9-otp
Version: 0.2.2
Summary: UNKNOWN
Home-page: UNKNOWN
License: UNKNOWN
Platform: UNKNOWN
Requires-Dist: requests
Requires-Dist: python-dotenv
